[
  {
    "eventName": "Chainless Challenge",
    "eventDate": "2026-05-03T00:00:00Z",
    "clubName": "Derby MTB Club",
    "state": "TAS",
    "eventUrl": "https://entryboss.cc/races/30557"
  },
  {
    "eventName": "Evandale – Nile Road Return",
    "eventDate": "2026-05-03T00:00:00Z",
    "clubName": "Northern Vets CC (Tasmania)",
    "state": "TAS",
    "eventUrl": "https://entryboss.cc/races/30422"
  },
  {
    "eventName": "LAUNCESTON BMX - NIGHT SERIES 2024 - SERIES PASS",
    "eventDate": "2026-05-09T00:00:00Z",
    "clubName": "Launceston BMX Club",
    "state": "TAS",
    "eventUrl": "https://entryboss.cc/races/20374"
  },
  {
    "eventName": "2025 Night Series - Series Entry (All 3 events)",
    "eventDate": "2026-05-09T00:00:00Z",
    "clubName": "Launceston BMX Club",
    "state": "TAS",
    "eventUrl": "https://entryboss.cc/races/27935"
  },
  {
    "eventName": "2026 Night Series - Series Entry - ALL 3 ROUNDS",
    "eventDate": "2026-05-09T00:00:00Z",
    "clubName": "Launceston BMX Club",
    "state": "TAS",
    "eventUrl": "https://entryboss.cc/races/30426"
  },
  {
    "eventName": "2026 Night Series - Round 1",
    "eventDate": "2026-05-09T00:00:00Z",
    "clubName": "Launceston BMX Club",
    "state": "TAS",
    "eventUrl": "https://entryboss.cc/races/30346"
  },
  {
    "eventName": "LAUNCESTON BMX - TWILIGHT SERIES 2021 - SERIES ENTRY",
    "eventDate": "2026-05-09T00:00:00Z",
    "clubName": "Launceston BMX Club",
    "state": "TAS",
    "eventUrl": "https://entryboss.cc/races/8627"
  },
  {
    "eventName": "LAUNCESTON BMX - TWILIGHT SERIES 2023 - SERIES PASS",
    "eventDate": "2026-05-09T00:00:00Z",
    "clubName": "Launceston BMX Club",
    "state": "TAS",
    "eventUrl": "https://entryboss.cc/races/14524"
  },
  {
    "eventName": "2026 AusCycling BMX State Series - RD3 Launceston",
    "eventDate": "2026-05-16T00:00:00Z",
    "clubName": "AusCycling (Tasmania)",
    "state": "TAS",
    "eventUrl": "https://entryboss.cc/races/28520"
  },
  {
    "eventName": "Cressy Road Series - Race 1",
    "eventDate": "2026-05-16T00:00:00Z",
    "clubName": "Launceston City Cycling Club",
    "state": "TAS",
    "eventUrl": "https://entryboss.cc/races/30313"
  },
  {
    "eventName": "Bracknell",
    "eventDate": "2026-05-17T00:00:00Z",
    "clubName": "Northern Vets CC (Tasmania)",
    "state": "TAS",
    "eventUrl": "https://entryboss.cc/races/30423"
  },
  {
    "eventName": "NW MTB Series - Winter in Paradise - Round 2",
    "eventDate": "2026-05-17T00:00:00Z",
    "clubName": "Mersey Mountain Bike Club",
    "state": "TAS",
    "eventUrl": "https://entryboss.cc/races/30131"
  },
  {
    "eventName": "Oatlands 50 - MyRide Super series event 3",
    "eventDate": "2026-05-23T00:00:00Z",
    "clubName": "Hobart Wheelers Dirt Devils CC",
    "state": "TAS",
    "eventUrl": "https://entryboss.cc/races/29982"
  },
  {
    "eventName": "Clash 4 Cash 2026",
    "eventDate": "2026-05-30T00:00:00Z",
    "clubName": "Southern City BMX",
    "state": "TAS",
    "eventUrl": "https://entryboss.cc/races/29800"
  },
  {
    "eventName": "Cressy Road Series - Race 2",
    "eventDate": "2026-05-30T00:00:00Z",
    "clubName": "Launceston City Cycling Club",
    "state": "TAS",
    "eventUrl": "https://entryboss.cc/races/30314"
  },
  {
    "eventName": "St Helens - Pedalheads MTB club Comeback Race - Icarus 2026",
    "eventDate": "2026-06-07T00:00:00Z",
    "clubName": "Pedal Heads",
    "state": "TAS",
    "eventUrl": "https://entryboss.cc/races/30513"
  },
  {
    "eventName": "2026 Night Series - Round 2",
    "eventDate": "2026-06-13T00:00:00Z",
    "clubName": "Launceston BMX Club",
    "state": "TAS",
    "eventUrl": "https://entryboss.cc/races/30424"
  },
  {
    "eventName": "NW MTB Series - Winter in Paradise - Round 3",
    "eventDate": "2026-06-14T00:00:00Z",
    "clubName": "Mersey Mountain Bike Club",
    "state": "TAS",
    "eventUrl": "https://entryboss.cc/races/30132"
  },
  {
    "eventName": "2026 Night Series - Round 3",
    "eventDate": "2026-06-20T00:00:00Z",
    "clubName": "Launceston BMX Club",
    "state": "TAS",
    "eventUrl": "https://entryboss.cc/races/30425"
  },
  {
    "eventName": "Cressy Road Series - Race 3",
    "eventDate": "2026-06-27T00:00:00Z",
    "clubName": "Launceston City Cycling Club",
    "state": "TAS",
    "eventUrl": "https://entryboss.cc/races/30315"
  },
  {
    "eventName": "2026 AusCycling BMX State Series - RD4 Southern City",
    "eventDate": "2026-06-27T00:00:00Z",
    "clubName": "AusCycling (Tasmania)",
    "state": "TAS",
    "eventUrl": "https://entryboss.cc/races/28521"
  },
  {
    "eventName": "NW MTB Series - Winter in Paradise - Round 4",
    "eventDate": "2026-07-26T00:00:00Z",
    "clubName": "Mersey Mountain Bike Club",
    "state": "TAS",
    "eventUrl": "https://entryboss.cc/races/30133"
  },
  {
    "eventName": "2026 AusCycling BMX State Series - RD5 Wynyard",
    "eventDate": "2026-08-15T00:00:00Z",
    "clubName": "AusCycling (Tasmania)",
    "state": "TAS",
    "eventUrl": "https://entryboss.cc/races/28522"
  },
  {
    "eventName": "NW MTB Series - Winter in Paradise - Round 5",
    "eventDate": "2026-08-23T00:00:00Z",
    "clubName": "Mersey Mountain Bike Club",
    "state": "TAS",
    "eventUrl": "https://entryboss.cc/races/30134"
  },
  {
    "eventName": "2026 AusCycling BMX State Series - RD6 Launceston",
    "eventDate": "2026-09-05T00:00:00Z",
    "clubName": "AusCycling (Tasmania)",
    "state": "TAS",
    "eventUrl": "https://entryboss.cc/races/28523"
  },
  {
    "eventName": "Plates \u0026 Holders",
    "eventDate": "2026-12-25T00:00:00Z",
    "clubName": "Northern Vets CC (Tasmania)",
    "state": "TAS",
    "eventUrl": "https://entryboss.cc/races/29716"
  }
]